{
  "posts": [
    {
      "id": "5000d03d-2bbb-4af9-9537-f2d160b99189",
      "title": "아바타 관람",
      "date": "2022-12-17",
      "userId": "변시윤",
      "comment": 1
    },
    {
      "id": "e81aee61-edb3-4c77-ba4c-61382502717a",
      "title": "팀 프로젝트",
      "date": "2022-12-23",
      "userId": "김재현",
      "comment": 1
    },
    {
      "id": "6c0eb62f-0be5-466d-9d1e-8e67c9f80c93",
      "title": "팀 프로젝트",
      "date": "2022-12-23",
      "userId": "정하나",
      "comment": 1
    },
    {
      "id": "3fce725a-0347-4668-afb6-227e3607ff5f",
      "title": "리덕스",
      "date": "2022-12-29",
      "desc": "asdsa",
      "userId": "이순재",
      "comment": 1
    },
    {
      "id": "395f55e6-82ef-4a50-ac4b-27f3a95cc27a",
      "title": "자바스크립트",
      "date": "2022-12-22",
      "desc": "444",
      "userId": "변시윤",
      "comment": 3
    },
    {
      "id": "f7094f1c-0261-451c-bc29-c7c3c2c93ac0",
      "title": "타입스크립트",
      "date": "2022-12-07",
      "desc": "555",
      "userId": "김재현",
      "comment": 1
    },
    {
      "id": "fc93a8dc-9e0a-4550-a455-41e2820f3d70",
      "title": "리덕스",
      "date": "2022-12-05",
      "desc": "555",
      "userId": "정하나",
      "comment": 2
    },
    {
      "id": "f4aaa3fb-5043-4dd6-9f7e-c6708f3675ee",
      "title": "",
      "date": "",
      "desc": ""
    },
    {
      "id": "e14b4929-6d8c-4130-8e8b-aa152322e767",
      "title": "",
      "date": "",
      "desc": ""
    },
    {
      "id": "d663f7f5-515c-49cd-a485-d447de49aaa1",
      "title": "",
      "date": "",
      "desc": ""
    },
    {
      "id": "40495d38-5b1d-4350-aa0d-a77c0e0f3be4",
      "title": "",
      "date": "",
      "desc": ""
    },
    {
      "id": "380b124a-03bc-4039-a2a5-993842ee862e",
      "title": "",
      "date": "",
      "desc": ""
    },
    {
      "id": "0a3e5393-f528-48a9-bda0-99d536b3505c",
      "title": "",
      "date": "",
      "desc": ""
    },
    {
      "id": "9e8ab0a4-a453-492a-afad-7b0079385d0b",
      "title": "",
      "date": "",
      "desc": ""
    },
    {
      "id": "bf3fa1a5-2e32-442a-a756-bb2b81219464",
      "title": "",
      "date": "",
      "desc": ""
    },
    {
      "id": "74305005-fd0c-49f1-85f6-94ff31064b14",
      "title": "",
      "date": "",
      "desc": ""
    },
    {
      "id": "524ab3fd-8ab6-4973-a2bc-4f45ba5b971f",
      "title": "",
      "date": "",
      "desc": ""
    },
    {
      "id": "e8546585-e0e6-422e-8682-8834061f3b92",
      "title": "",
      "date": "",
      "desc": ""
    },
    {
      "id": "bd8ef94c-0f5f-4d17-9acc-4953a8e4980a",
      "title": "",
      "date": "",
      "desc": ""
    },
    {
      "id": "43ad8336-6cd8-41b2-860f-cef4c70eb5ca",
      "title": "",
      "date": "",
      "desc": ""
    }
  ]
}