{
  "posts": [
    {
      "id": "919eeaa8-0f25-4edb-948b-0d0e18aeb843",
      "title": "1231",
      "userId": "이순재",
      "date": "2022-12-09",
      "desc": "하하하",
      "comments": [
        {
          "id": "919eeaa8-0f25-4edb-948b-0d0e18aeb843",
          "commentId": "1222",
          "name": "김재현",
          "password": "1234",
          "comment": "hi",
          "date": "2022-12-09"
        },
        {
          "id": "919eeaa8-0f25-4edb-948b-0d0e18aeb843",
          "commentId": "9c950f7b-fcbd-48f7-8844-fcd20943085d",
          "name": "test",
          "password": "1234",
          "comment": "1234",
          "date": "function toISOString() { [native code] }"
        },
        {
          "id": "919eeaa8-0f25-4edb-948b-0d0e18aeb843",
          "commentId": "70097f27-d9e2-411d-90d0-161f0b87631c",
          "name": "123",
          "password": "1234",
          "comment": "123",
          "date": "function toISOString() { [native code] }"
        }
      ]
    },
    {
      "id": "7d0e9055-0d53-40d8-a5ac-6bb67177cc73",
      "title": "123231",
      "userId": "김재현",
      "date": "2022-12-08",
      "desc": "123123123",
      "comments": []
    },
    {
      "id": "5928a4c8-7230-474d-9ba3-7cea3745a409",
      "title": "이름 선택한 데이터",
      "userId": "",
      "date": "2022-12-21",
      "desc": "순재님으로 선택",
      "comments": [
        {
          "id": "5928a4c8-7230-474d-9ba3-7cea3745a409",
          "commentId": "513f5c6b-16e9-46e8-a383-04b508eb554b",
          "name": "이순재",
          "password": "1234",
          "comment": "이순재",
          "date": "function toISOString() { [native code] }"
        },
        {
          "id": "5928a4c8-7230-474d-9ba3-7cea3745a409",
          "commentId": "3c813935-9399-45b4-8ec1-ce60187d7e1f",
          "name": "테스트",
          "password": "1234",
          "comment": "ㅌㅅㅌ",
          "date": "function toISOString() { [native code] }"
        },
        {
          "id": "5928a4c8-7230-474d-9ba3-7cea3745a409",
          "commentId": "aa4d6771-be13-440e-b03c-71624cc59aea",
          "name": "ㅇㅇㅇㅇ",
          "password": "ㅇddd",
          "comment": "ㅇㅇㅇㅇ",
          "date": "function toISOString() { [native code] }"
        }
      ]
    }
  ]
}